cloudmesh_oracle-4.1.4-nspkg.pth
cloudmesh/oracle/__init__.py
cloudmesh/oracle/__version__.py
cloudmesh/oracle/command/__init__.py
cloudmesh/oracle/command/oracle.py
cloudmesh/oracle/compute/Provider.py
cloudmesh/oracle/compute/__init__.py
cloudmesh/oracle/storage/Provider.py
cloudmesh/oracle/storage/__init__.py
cloudmesh_oracle-4.1.4.dist-info/LICENSE
cloudmesh_oracle-4.1.4.dist-info/METADATA
cloudmesh_oracle-4.1.4.dist-info/WHEEL
cloudmesh_oracle-4.1.4.dist-info/namespace_packages.txt
cloudmesh_oracle-4.1.4.dist-info/top_level.txt
cloudmesh_oracle-4.1.4.dist-info/RECORD
